b_twilio_sdk_layer/__init__.py
b_twilio_sdk_layer/layer.py
b_twilio_sdk_layer-1.0.1.dist-info/LICENSE
b_twilio_sdk_layer-1.0.1.dist-info/METADATA
b_twilio_sdk_layer-1.0.1.dist-info/WHEEL
b_twilio_sdk_layer-1.0.1.dist-info/top_level.txt
b_twilio_sdk_layer-1.0.1.dist-info/RECORD
