Metadata-Version: 2.1
Name: b-twilio-sdk-layer
Version: 1.0.1
Summary: AWS CDK based lambda layer including Twilio SDK.
Home-page: https://github.com/biomapas/B.TwilioSdkLayer.git
Author: Laimonas Sutkus
Author-email: laimonas.sutkus@biomapas.com
License: Apache License 2.0
Keywords: AWS CDK Lambda Layer Twilio
Platform: UNKNOWN
Classifier: Programming Language :: Python :: 3
Classifier: Operating System :: OS Independent
Requires-Dist: aws-cdk.core (<2.0.0,>=1.54.0)
Requires-Dist: aws-cdk.aws-lambda (<2.0.0,>=1.54.0)
Requires-Dist: b-cfn-lambda-layer (<2.0.0,>=1.1.1)
